{"v":"5.12.2","fr":20,"ip":0,"op":40,"w":900,"h":900,"nm":"directions (2)","ddd":0,"assets":[],"layers":[{"ddd":0,"ind":1,"ty":4,"nm":"Capa 1 Outlines","sr":1,"ks":{"o":{"a":0,"k":100,"ix":11},"r":{"a":0,"k":0,"ix":10},"p":{"a":0,"k":[481.718,500.327,0],"ix":2,"l":2},"a":{"a":0,"k":[222.905,222.885,0],"ix":1,"l":2},"s":{"a":0,"k":[100,100,100],"ix":6,"l":2}},"ao":0,"shapes":[{"ty":"gr","it":[{"ind":0,"ty":"sh","ix":1,"ks":{"a":0,"k":{"i":[[0,0],[35.316,-34.962]],"o":[[-35.355,35.355],[0,0]],"v":[[52.66,-52.483],[-52.66,52.483]],"c":false},"ix":2},"nm":"Path 1","mn":"ADBE Vector Shape - Group","hd":false},{"ty":"st","c":{"a":0,"k":[0.6275,0.549,0.4627,1],"ix":3},"o":{"a":0,"k":100,"ix":4},"w":{"a":0,"k":15,"ix":5},"lc":2,"lj":2,"bm":0,"nm":"Stroke 1","mn":"ADBE Vector Graphic - Stroke","hd":false},{"ty":"tr","p":{"a":0,"k":[90.16,270.976],"ix":2},"a":{"a":0,"k":[0,0],"ix":1},"s":{"a":0,"k":[100,100],"ix":3},"r":{"a":0,"k":0,"ix":6},"o":{"a":0,"k":100,"ix":7},"sk":{"a":0,"k":0,"ix":4},"sa":{"a":0,"k":0,"ix":5},"nm":"Transform"}],"nm":"Group 1","np":2,"cix":2,"bm":0,"ix":1,"mn":"ADBE Vector Group","hd":false},{"ty":"gr","it":[{"ind":0,"ty":"sh","ix":1,"ks":{"a":0,"k":{"i":[[0,0],[-59.928,60.282]],"o":[[60.022,-59.668],[0,0]],"v":[[-90.027,90.027],[90.027,-90.027]],"c":false},"ix":2},"nm":"Path 1","mn":"ADBE Vector Shape - Group","hd":false},{"ty":"st","c":{"a":0,"k":[0.6275,0.549,0.4627,1],"ix":3},"o":{"a":0,"k":100,"ix":4},"w":{"a":0,"k":15,"ix":5},"lc":2,"lj":2,"bm":0,"nm":"Stroke 1","mn":"ADBE Vector Graphic - Stroke","hd":false},{"ty":"tr","p":{"a":0,"k":[212.422,318.243],"ix":2},"a":{"a":0,"k":[0,0],"ix":1},"s":{"a":0,"k":[100,100],"ix":3},"r":{"a":0,"k":0,"ix":6},"o":{"a":0,"k":100,"ix":7},"sk":{"a":0,"k":0,"ix":4},"sa":{"a":0,"k":0,"ix":5},"nm":"Transform"}],"nm":"Group 2","np":2,"cix":2,"bm":0,"ix":2,"mn":"ADBE Vector Group","hd":false},{"ty":"gr","it":[{"ind":0,"ty":"sh","ix":1,"ks":{"a":1,"k":[{"i":{"x":0.667,"y":1},"o":{"x":0.333,"y":0},"t":0,"s":[{"i":[[0,0],[0,0],[0,0],[0,13.362],[0,0],[8.285,0],[0,0],[-9.449,-9.448],[0,0],[0,0]],"o":[[0,0],[0,0],[9.448,9.448],[0,0],[0,-8.284],[0,0],[-13.362,0],[0,0],[0,0],[0,0]],"v":[[5.406,84.751],[43.255,46.902],[64.448,68.095],[90.052,57.489],[90.055,-69.752],[75.055,-84.751],[-52.185,-84.748],[-62.791,-59.144],[-41.599,-37.951],[-90.055,10.505]],"c":false}]},{"i":{"x":0.667,"y":1},"o":{"x":0.333,"y":0},"t":6,"s":[{"i":[[0,0],[0,0],[0,0],[0,13.362],[0,0],[8.285,0],[0,0],[-9.449,-9.448],[0,0],[0,0]],"o":[[0,0],[0,0],[9.448,9.448],[0,0],[0,-8.284],[0,0],[-13.362,0],[0,0],[0,0],[0,0]],"v":[[5.406,84.751],[87.462,3.108],[108.654,24.301],[134.258,13.695],[134.261,-113.546],[119.262,-128.545],[-7.979,-128.542],[-18.584,-102.938],[2.608,-81.745],[-90.055,10.505]],"c":false}]},{"i":{"x":0.667,"y":1},"o":{"x":0.333,"y":0},"t":12,"s":[{"i":[[0,0],[0,0],[0,0],[0,13.362],[0,0],[8.285,0],[0,0],[-9.449,-9.448],[0,0],[0,0]],"o":[[0,0],[0,0],[9.448,9.448],[0,0],[0,-8.284],[0,0],[-13.362,0],[0,0],[0,0],[0,0]],"v":[[5.406,84.751],[43.255,46.902],[64.448,68.095],[90.052,57.489],[90.055,-69.752],[75.055,-84.751],[-52.185,-84.748],[-62.791,-59.144],[-41.599,-37.951],[-90.055,10.505]],"c":false}]},{"i":{"x":0.667,"y":1},"o":{"x":0.333,"y":0},"t":18,"s":[{"i":[[0,0],[0,0],[0,0],[0,13.362],[0,0],[8.285,0],[0,0],[-9.449,-9.448],[0,0],[0,0]],"o":[[0,0],[0,0],[9.448,9.448],[0,0],[0,-8.284],[0,0],[-13.362,0],[0,0],[0,0],[0,0]],"v":[[5.406,84.751],[87.462,3.108],[108.654,24.301],[134.258,13.695],[134.261,-113.546],[119.262,-128.545],[-7.979,-128.542],[-18.584,-102.938],[2.608,-81.745],[-90.055,10.505]],"c":false}]},{"t":24,"s":[{"i":[[0,0],[0,0],[0,0],[0,13.362],[0,0],[8.285,0],[0,0],[-9.449,-9.448],[0,0],[0,0]],"o":[[0,0],[0,0],[9.448,9.448],[0,0],[0,-8.284],[0,0],[-13.362,0],[0,0],[0,0],[0,0]],"v":[[5.406,84.751],[43.255,46.902],[64.448,68.095],[90.052,57.489],[90.055,-69.752],[75.055,-84.751],[-52.185,-84.748],[-62.791,-59.144],[-41.599,-37.951],[-90.055,10.505]],"c":false}]}],"ix":2},"nm":"Path 1","mn":"ADBE Vector Shape - Group","hd":false},{"ty":"st","c":{"a":0,"k":[0.6275,0.549,0.4627,1],"ix":3},"o":{"a":0,"k":100,"ix":4},"w":{"a":0,"k":15,"ix":5},"lc":2,"lj":2,"bm":0,"nm":"Stroke 1","mn":"ADBE Vector Graphic - Stroke","hd":false},{"ty":"tr","p":{"a":0,"k":[318.256,122.252],"ix":2},"a":{"a":0,"k":[0,0],"ix":1},"s":{"a":0,"k":[100,100],"ix":3},"r":{"a":0,"k":0,"ix":6},"o":{"a":0,"k":100,"ix":7},"sk":{"a":0,"k":0,"ix":4},"sa":{"a":0,"k":0,"ix":5},"nm":"Transform"}],"nm":"Group 3","np":2,"cix":2,"bm":0,"ix":3,"mn":"ADBE Vector Group","hd":false},{"ty":"gr","it":[{"ind":0,"ty":"sh","ix":1,"ks":{"a":1,"k":[{"i":{"x":0.667,"y":1},"o":{"x":0.333,"y":0},"t":0,"s":[{"i":[[0,0],[-1.414,-16.97],[-8.485,1.414],[-4.242,2.828],[-8.485,4.242],[-14.142,-18.385]],"o":[[-0.028,16.662],[1.414,8.485],[4.95,-0.707],[7.071,-5.657],[15.556,16.97],[0,0]],"v":[[-46.641,-43.687],[-46.669,6.917],[-29.699,19.645],[-17.678,13.281],[0.707,-5.104],[48.083,43.687]],"c":false}]},{"i":{"x":0.667,"y":1},"o":{"x":0.333,"y":0},"t":6,"s":[{"i":[[0,0],[-1.414,-16.97],[-8.485,1.414],[-4.242,2.828],[-8.485,4.242],[-14.142,-18.385]],"o":[[-0.028,16.662],[1.414,8.485],[4.95,-0.707],[7.071,-5.657],[15.556,16.97],[0,0]],"v":[[-89.55,-85.777],[-89.578,-35.174],[-72.608,-22.445],[-60.587,-28.81],[-42.202,-47.194],[48.083,43.687]],"c":false}]},{"i":{"x":0.667,"y":1},"o":{"x":0.333,"y":0},"t":12,"s":[{"i":[[0,0],[-1.414,-16.97],[-8.485,1.414],[-4.242,2.828],[-8.485,4.242],[-14.142,-18.385]],"o":[[-0.028,16.662],[1.414,8.485],[4.95,-0.707],[7.071,-5.657],[15.556,16.97],[0,0]],"v":[[-46.641,-43.687],[-46.669,6.917],[-29.699,19.645],[-17.678,13.281],[0.707,-5.104],[48.083,43.687]],"c":false}]},{"i":{"x":0.667,"y":1},"o":{"x":0.333,"y":0},"t":18,"s":[{"i":[[0,0],[-1.414,-16.97],[-8.485,1.414],[-4.242,2.828],[-8.485,4.242],[-14.142,-18.385]],"o":[[-0.028,16.662],[1.414,8.485],[4.95,-0.707],[7.071,-5.657],[15.556,16.97],[0,0]],"v":[[-89.55,-85.777],[-89.578,-35.174],[-72.608,-22.445],[-60.587,-28.81],[-42.202,-47.194],[48.083,43.687]],"c":false}]},{"t":24,"s":[{"i":[[0,0],[-1.414,-16.97],[-8.485,1.414],[-4.242,2.828],[-8.485,4.242],[-14.142,-18.385]],"o":[[-0.028,16.662],[1.414,8.485],[4.95,-0.707],[7.071,-5.657],[15.556,16.97],[0,0]],"v":[[-46.641,-43.687],[-46.669,6.917],[-29.699,19.645],[-17.678,13.281],[0.707,-5.104],[48.083,43.687]],"c":false}]}],"ix":2},"nm":"Path 1","mn":"ADBE Vector Shape - Group","hd":false},{"ty":"st","c":{"a":0,"k":[0.4157,0.6941,0.7255,1],"ix":3},"o":{"a":0,"k":100,"ix":4},"w":{"a":0,"k":15,"ix":5},"lc":2,"lj":2,"bm":0,"nm":"Stroke 1","mn":"ADBE Vector Graphic - Stroke","hd":false},{"ty":"tr","p":{"a":0,"k":[94.736,174.807],"ix":2},"a":{"a":0,"k":[0,0],"ix":1},"s":{"a":0,"k":[100,100],"ix":3},"r":{"a":0,"k":0,"ix":6},"o":{"a":0,"k":100,"ix":7},"sk":{"a":0,"k":0,"ix":4},"sa":{"a":0,"k":0,"ix":5},"nm":"Transform"}],"nm":"Group 4","np":2,"cix":2,"bm":0,"ix":4,"mn":"ADBE Vector Group","hd":false},{"ty":"gr","it":[{"ind":0,"ty":"sh","ix":1,"ks":{"a":1,"k":[{"i":{"x":0.667,"y":1},"o":{"x":0.333,"y":0},"t":0,"s":[{"i":[[0,0],[0,0],[0,0],[13.361,0],[0,0],[0,-8.284],[0,0]],"o":[[0,0],[0,0],[9.449,-9.448],[0,0],[-8.284,-0.001],[0,0],[0,0]],"v":[[90.054,47.628],[41.598,-0.827],[62.791,-22.02],[52.186,-47.624],[-75.055,-47.627],[-90.054,-32.628],[-90.053,15.993]],"c":false}]},{"i":{"x":0.667,"y":1},"o":{"x":0.333,"y":0},"t":6,"s":[{"i":[[0,0],[0,0],[0,0],[13.361,0],[0,0],[0,-8.284],[0,0]],"o":[[0,0],[0,0],[9.449,-9.448],[0,0],[-8.284,-0.001],[0,0],[0,0]],"v":[[90.054,47.628],[-1.311,-42.918],[19.882,-64.111],[9.277,-89.715],[-117.964,-89.718],[-132.963,-74.719],[-132.962,-26.098]],"c":false}]},{"i":{"x":0.667,"y":1},"o":{"x":0.333,"y":0},"t":12,"s":[{"i":[[0,0],[0,0],[0,0],[13.361,0],[0,0],[0,-8.284],[0,0]],"o":[[0,0],[0,0],[9.449,-9.448],[0,0],[-8.284,-0.001],[0,0],[0,0]],"v":[[90.054,47.628],[41.598,-0.827],[62.791,-22.02],[52.186,-47.624],[-75.055,-47.627],[-90.054,-32.628],[-90.053,15.993]],"c":false}]},{"i":{"x":0.667,"y":1},"o":{"x":0.333,"y":0},"t":18,"s":[{"i":[[0,0],[0,0],[0,0],[13.361,0],[0,0],[0,-8.284],[0,0]],"o":[[0,0],[0,0],[9.449,-9.448],[0,0],[-8.284,-0.001],[0,0],[0,0]],"v":[[90.054,47.628],[-1.311,-42.918],[19.882,-64.111],[9.277,-89.715],[-117.964,-89.718],[-132.963,-74.719],[-132.962,-26.098]],"c":false}]},{"t":24,"s":[{"i":[[0,0],[0,0],[0,0],[13.361,0],[0,0],[0,-8.284],[0,0]],"o":[[0,0],[0,0],[9.449,-9.448],[0,0],[-8.284,-0.001],[0,0],[0,0]],"v":[[90.054,47.628],[41.598,-0.827],[62.791,-22.02],[52.186,-47.624],[-75.055,-47.627],[-90.054,-32.628],[-90.053,15.993]],"c":false}]}],"ix":2},"nm":"Path 1","mn":"ADBE Vector Shape - Group","hd":false},{"ty":"st","c":{"a":0,"k":[0.4157,0.6941,0.7255,1],"ix":3},"o":{"a":0,"k":100,"ix":4},"w":{"a":0,"k":15,"ix":5},"lc":2,"lj":2,"bm":0,"nm":"Stroke 1","mn":"ADBE Vector Graphic - Stroke","hd":false},{"ty":"tr","p":{"a":0,"k":[138.148,85.128],"ix":2},"a":{"a":0,"k":[0,0],"ix":1},"s":{"a":0,"k":[100,100],"ix":3},"r":{"a":0,"k":0,"ix":6},"o":{"a":0,"k":100,"ix":7},"sk":{"a":0,"k":0,"ix":4},"sa":{"a":0,"k":0,"ix":5},"nm":"Transform"}],"nm":"Group 5","np":2,"cix":2,"bm":0,"ix":5,"mn":"ADBE Vector Group","hd":false}],"ip":0,"op":40,"st":0,"ct":1,"bm":0}],"markers":[],"props":{}}